tiktok_info/__init__.py
tiktok_info/info.py
tiktok_info-10.10.10.dist-info/LICENSE
tiktok_info-10.10.10.dist-info/WHEEL
tiktok_info-10.10.10.dist-info/METADATA
tiktok_info-10.10.10.dist-info/RECORD
