Metadata-Version: 2.3
Name: tiktok_info
Version: 10.10.10
Summary: TikTok Info: Modul untuk mengambil dan memproses informasi dari TikTok.
Author-email: bilalsbxp <bilalsaputra641@gmail.com>
Classifier: License :: OSI Approved :: MIT License
Project-URL: Home, https://pypi.org/project/tiktok_info/
